{
    "b8e47b7d33": {
        "view://preview@en_US": {
            "dev": "c8210ada0a"
        },
        "component://force/lds@en_US": {
            "dev": "91742f4074"
        },
        "view://mainLayout@en_US": {
            "dev": "67133358b1"
        },
        "view://home@en_US": {
            "dev": "8641da935e"
        }
    },
    "a6e8a9c54f": {
        "view://preview@en_US": {
            "dev": "c8210ada0a"
        },
        "component://force/lds@en_US": {
            "dev": "91742f4074"
        },
        "view://mainLayout@en_US": {
            "dev": "67133358b1"
        },
        "view://home@en_US": {
            "dev": "8641da935e"
        }
    }
}